{"status": "READY", "relations": [], "name": "review_27.txt", "language": "EN", "text": "my suv and the service rep was very helpful and friendly. i will be going back here for all my vehicle needs.\n", "createdDate": 0, "typeResolved": true, "documentSet": [], "preannotation": ["PRE_LW"], "version": 3, "sentences": [{"tokens": [{"text": "my", "begin": 0, "end": 2, "id": "s0-t0", "whiteSpace": false}, {"text": "suv", "begin": 3, "end": 6, "id": "s0-t1", "whiteSpace": false}, {"text": "and", "begin": 7, "end": 10, "id": "s0-t2", "whiteSpace": false}, {"text": "the", "begin": 11, "end": 14, "id": "s0-t3", "whiteSpace": false}, {"text": "service", "begin": 15, "end": 22, "id": "s0-t4", "whiteSpace": false}, {"text": "rep", "begin": 23, "end": 26, "id": "s0-t5", "whiteSpace": false}, {"text": "was", "begin": 27, "end": 30, "id": "s0-t6", "whiteSpace": false}, {"text": "very", "begin": 31, "end": 35, "id": "s0-t7", "whiteSpace": false}, {"text": "helpful", "begin": 36, "end": 43, "id": "s0-t8", "whiteSpace": false}, {"text": "and", "begin": 44, "end": 47, "id": "s0-t9", "whiteSpace": false}, {"text": "friendly", "begin": 48, "end": 56, "id": "s0-t10", "whiteSpace": false}, {"text": ".", "begin": 56, "end": 57, "id": "s0-t11", "whiteSpace": false}], "text": "my suv and the service rep was very helpful and friendly.", "begin": 0, "end": 57, "id": "s0"}, {"tokens": [{"text": "i", "begin": 58, "end": 59, "id": "s1-t0", "whiteSpace": false}, {"text": "will", "begin": 60, "end": 64, "id": "s1-t1", "whiteSpace": false}, {"text": "be", "begin": 65, "end": 67, "id": "s1-t2", "whiteSpace": false}, {"text": "going", "begin": 68, "end": 73, "id": "s1-t3", "whiteSpace": false}, {"text": "back", "begin": 74, "end": 78, "id": "s1-t4", "whiteSpace": false}, {"text": "here", "begin": 79, "end": 83, "id": "s1-t5", "whiteSpace": false}, {"text": "for", "begin": 84, "end": 87, "id": "s1-t6", "whiteSpace": false}, {"text": "all", "begin": 88, "end": 91, "id": "s1-t7", "whiteSpace": false}, {"text": "my", "begin": 92, "end": 94, "id": "s1-t8", "whiteSpace": false}, {"text": "vehicle", "begin": 95, "end": 102, "id": "s1-t9", "whiteSpace": false}, {"text": "needs", "begin": 103, "end": 108, "id": "s1-t10", "whiteSpace": false}, {"text": ".", "begin": 108, "end": 109, "id": "s1-t11", "whiteSpace": false}], "text": "i will be going back here for all my vehicle needs.", "begin": 58, "end": 109, "id": "s1"}], "modifiedDate": 1590525833573, "docLength": 0, "mentions": [], "corefs": [], "id": "8a2a6550-9f91-11ea-9fed-efe5f3c36d5e-26", "userResolved": false}